yeedu/__init__.py
yeedu/hooks/__init__.py
yeedu/hooks/yeedu.py
yeedu/operators/__init__.py
yeedu/operators/healthcheck_operator.py
yeedu/operators/job_operator.py
yeedu/operators/notebook_operator.py
yeedu/operators/yeedu.py
airflow_yeedu_operator-2.9.0.dist-info/LICENSE
airflow_yeedu_operator-2.9.0.dist-info/METADATA
airflow_yeedu_operator-2.9.0.dist-info/WHEEL
airflow_yeedu_operator-2.9.0.dist-info/top_level.txt
airflow_yeedu_operator-2.9.0.dist-info/RECORD
