Metadata-Version: 2.1
Name: airflow-yeedu-operator
Version: 2.9.0
Summary: Submission and monitoring of jobs and notebooks using the Yeedu API in Apache Airflow. 
Author: Yeedu
Author-email: yeedu@modak.com
License: All Rights Reserved
Project-URL: GitHub, https://github.com/yeedu-io/Apache-Airflow-Operator
License-File: LICENSE
Requires-Dist: apache-airflow >=2.5.0
Requires-Dist: requests >=2.27
Requires-Dist: websocket-client >=1.8.0
Requires-Dist: rel >=0.4.9.19
